{
  "globals": {
    "site_title": "welling guzman's blog",
    "site_description": "Welling Guzman is a software engineer, and this is his writing in third person.",
    "site_url": "http://wellingguzman.com",
    "analytics": "UA-37732822-1",
    "main_nav": {
      "home": "/",
      "notes": "/notes",
      "about": "/about"
    },
    "footer_nav": {
      "about": "/about",
      "twitter": "https://twitter.com/WellingGuzman",
      "github": "https://github.com/WellingGuzman"
    }
  }
}
